[{"data":{"meta_id":"445","comment_id":"67","meta_key":"akismet_history","meta_value":"a:4:{s:4:\"time\";d:1370606673.5934140682220458984375;s:7:\"message\";s:92:\"Akismet was unable to check this comment (response: ), will automatically retry again later.\";s:5:\"event\";s:11:\"check-error\";s:4:\"user\";s:0:\"\";}"}},{"data":{"meta_id":"447","comment_id":"67","meta_key":"rating","meta_value":"3"}},{"data":{"meta_id":"448","comment_id":"67","meta_key":"akismet_history","meta_value":"a:4:{s:4:\"time\";d:1370607949.19136905670166015625;s:7:\"message\";s:46:\"wooteam changed the comment status to approved\";s:5:\"event\";s:15:\"status-approved\";s:4:\"user\";s:7:\"wooteam\";}"}},{"data":{"meta_id":"449","comment_id":"68","meta_key":"akismet_error","meta_value":"1370620465"}},{"data":{"meta_id":"450","comment_id":"68","meta_key":"akismet_history","meta_value":"a:4:{s:4:\"time\";d:1370620465.89346790313720703125;s:7:\"message\";s:92:\"Akismet was unable to check this comment (response: ), will automatically retry again later.\";s:5:\"event\";s:11:\"check-error\";s:4:\"user\";s:0:\"\";}"}},{"data":{"meta_id":"452","comment_id":"68","meta_key":"rating","meta_value":"5"}},{"data":{"meta_id":"453","comment_id":"68","meta_key":"akismet_history","meta_value":"a:4:{s:4:\"time\";d:1370620633.92792606353759765625;s:7:\"message\";s:46:\"wooteam changed the comment status to approved\";s:5:\"event\";s:15:\"status-approved\";s:4:\"user\";s:7:\"wooteam\";}"}},{"data":{"meta_id":"454","comment_id":"69","meta_key":"akismet_error","meta_value":"1370605945"}},{"data":{"meta_id":"455","comment_id":"69","meta_key":"akismet_history","meta_value":"a:4:{s:4:\"time\";d:1370605945.8927509784698486328125;s:7:\"message\";s:92:\"Akismet was unable to check this comment (response: ), will automatically retry again later.\";s:5:\"event\";s:11:\"check-error\";s:4:\"user\";s:0:\"\";}"}},{"data":{"meta_id":"457","comment_id":"69","meta_key":"rating","meta_value":"4"}},{"data":{"meta_id":"458","comment_id":"69","meta_key":"akismet_history","meta_value":"a:4:{s:4:\"time\";d:1370607928.4240779876708984375;s:7:\"message\";s:46:\"wooteam changed the comment status to approved\";s:5:\"event\";s:15:\"status-approved\";s:4:\"user\";s:7:\"wooteam\";}"}},{"data":{"meta_id":"459","comment_id":"70","meta_key":"akismet_error","meta_value":"1370606196"}},{"data":{"meta_id":"460","comment_id":"70","meta_key":"akismet_history","meta_value":"a:4:{s:4:\"time\";d:1370606196.096724987030029296875;s:7:\"message\";s:92:\"Akismet was unable to check this comment (response: ), will automatically retry again later.\";s:5:\"event\";s:11:\"check-error\";s:4:\"user\";s:0:\"\";}"}},{"data":{"meta_id":"462","comment_id":"70","meta_key":"rating","meta_value":"3"}},{"data":{"meta_id":"463","comment_id":"70","meta_key":"akismet_history","meta_value":"a:4:{s:4:\"time\";d:1370607938.78227710723876953125;s:7:\"message\";s:46:\"wooteam changed the comment status to approved\";s:5:\"event\";s:15:\"status-approved\";s:4:\"user\";s:7:\"wooteam\";}"}},{"data":{"meta_id":"464","comment_id":"71","meta_key":"akismet_error","meta_value":"1370607565"}},{"data":{"meta_id":"465","comment_id":"71","meta_key":"akismet_history","meta_value":"a:4:{s:4:\"time\";d:1370607565.8578360080718994140625;s:7:\"message\";s:92:\"Akismet was unable to check this comment (response: ), will automatically retry again later.\";s:5:\"event\";s:11:\"check-error\";s:4:\"user\";s:0:\"\";}"}},{"data":{"meta_id":"467","comment_id":"71","meta_key":"rating","meta_value":"5"}},{"data":{"meta_id":"468","comment_id":"71","meta_key":"akismet_history","meta_value":"a:4:{s:4:\"time\";d:1370607952.2542870044708251953125;s:7:\"message\";s:46:\"wooteam changed the comment status to approved\";s:5:\"event\";s:15:\"status-approved\";s:4:\"user\";s:7:\"wooteam\";}"}},{"data":{"meta_id":"469","comment_id":"72","meta_key":"akismet_error","meta_value":"1370609989"}}]