[{"data":{"meta_id":"4640","post_id":"1106","meta_key":"course_price_billing_t3","meta_value":"D"}},{"data":{"meta_id":"4641","post_id":"1106","meta_key":"_sfwd-courses","meta_value":"a:10:{s:29:\"sfwd-courses_course_materials\";s:241:\"&lt;a href=&quot;https:\/\/www.youtube.com\/watch?v=MSYw502dJNY&amp;list=PL8dPuuaLjXtOeEc9ME62zTfqc0h6Pe8vb&quot;&gt;Videos from youtube&lt;\/a&gt;\r\n&lt;a href=&quot;https:\/\/en.wikipedia.org\/wiki\/Literature&quot;&gt;Literature textbook&lt;\/a&gt;\";s:30:\"sfwd-courses_course_price_type\";s:6:\"paynow\";s:30:\"sfwd-courses_custom_button_url\";s:0:\"\";s:25:\"sfwd-courses_course_price\";s:0:\"\";s:31:\"sfwd-courses_course_access_list\";s:2:\"13\";s:34:\"sfwd-courses_course_lesson_orderby\";s:0:\"\";s:32:\"sfwd-courses_course_lesson_order\";s:0:\"\";s:32:\"sfwd-courses_course_prerequisite\";s:1:\"0\";s:31:\"sfwd-courses_expire_access_days\";s:0:\"\";s:24:\"sfwd-courses_certificate\";s:1:\"0\";}"}},{"data":{"meta_id":"4642","post_id":"1106","meta_key":"_badgeos_log_achievement_id","meta_value":null}},{"data":{"meta_id":"4643","post_id":"1107","meta_key":"_boss_edu_post_video","meta_value":"https:\/\/youtu.be\/MSYw502dJNY?list=PL8dPuuaLjXtOeEc9ME62zTfqc0h6Pe8vb"}},{"data":{"meta_id":"4644","post_id":"1107","meta_key":"bp_course_group","meta_value":"7"}},{"data":{"meta_id":"4645","post_id":"1107","meta_key":"course_price_billing_p3","meta_value":""}},{"data":{"meta_id":"4646","post_id":"1107","meta_key":"course_price_billing_t3","meta_value":"D"}},{"data":{"meta_id":"4647","post_id":"1107","meta_key":"_sfwd-courses","meta_value":"a:10:{s:29:\"sfwd-courses_course_materials\";s:241:\"&lt;a href=&quot;https:\/\/www.youtube.com\/watch?v=MSYw502dJNY&amp;list=PL8dPuuaLjXtOeEc9ME62zTfqc0h6Pe8vb&quot;&gt;Videos from youtube&lt;\/a&gt;\r\n&lt;a href=&quot;https:\/\/en.wikipedia.org\/wiki\/Literature&quot;&gt;Literature textbook&lt;\/a&gt;\";s:30:\"sfwd-courses_course_price_type\";s:4:\"free\";s:30:\"sfwd-courses_custom_button_url\";s:0:\"\";s:25:\"sfwd-courses_course_price\";s:0:\"\";s:31:\"sfwd-courses_course_access_list\";s:2:\"13\";s:34:\"sfwd-courses_course_lesson_orderby\";s:0:\"\";s:32:\"sfwd-courses_course_lesson_order\";s:0:\"\";s:32:\"sfwd-courses_course_prerequisite\";s:1:\"0\";s:31:\"sfwd-courses_expire_access_days\";s:0:\"\";s:24:\"sfwd-courses_certificate\";s:1:\"0\";}"}},{"data":{"meta_id":"4648","post_id":"1107","meta_key":"_badgeos_log_achievement_id","meta_value":null}},{"data":{"meta_id":"4649","post_id":"1108","meta_key":"_boss_edu_post_video","meta_value":"https:\/\/youtu.be\/MSYw502dJNY?list=PL8dPuuaLjXtOeEc9ME62zTfqc0h6Pe8vb"}},{"data":{"meta_id":"4650","post_id":"1108","meta_key":"bp_course_group","meta_value":"7"}},{"data":{"meta_id":"4651","post_id":"1108","meta_key":"course_price_billing_p3","meta_value":""}},{"data":{"meta_id":"4652","post_id":"1108","meta_key":"course_price_billing_t3","meta_value":"D"}},{"data":{"meta_id":"4653","post_id":"1108","meta_key":"_sfwd-courses","meta_value":"a:10:{s:29:\"sfwd-courses_course_materials\";s:241:\"&lt;a href=&quot;https:\/\/www.youtube.com\/watch?v=MSYw502dJNY&amp;list=PL8dPuuaLjXtOeEc9ME62zTfqc0h6Pe8vb&quot;&gt;Videos from youtube&lt;\/a&gt;\r\n&lt;a href=&quot;https:\/\/en.wikipedia.org\/wiki\/Literature&quot;&gt;Literature textbook&lt;\/a&gt;\";s:30:\"sfwd-courses_course_price_type\";s:4:\"free\";s:30:\"sfwd-courses_custom_button_url\";s:0:\"\";s:25:\"sfwd-courses_course_price\";s:0:\"\";s:31:\"sfwd-courses_course_access_list\";s:2:\"13\";s:34:\"sfwd-courses_course_lesson_orderby\";s:0:\"\";s:32:\"sfwd-courses_course_lesson_order\";s:0:\"\";s:32:\"sfwd-courses_course_prerequisite\";s:1:\"0\";s:31:\"sfwd-courses_expire_access_days\";s:0:\"\";s:24:\"sfwd-courses_certificate\";s:1:\"0\";}"}},{"data":{"meta_id":"4654","post_id":"1108","meta_key":"_badgeos_log_achievement_id","meta_value":null}},{"data":{"meta_id":"4655","post_id":"1109","meta_key":"_badgeos_log_achievement_id","meta_value":null}},{"data":{"meta_id":"4656","post_id":"1110","meta_key":"_badgeos_log_achievement_id","meta_value":null}},{"data":{"meta_id":"4657","post_id":"1111","meta_key":"_badgeos_log_achievement_id","meta_value":null}},{"data":{"meta_id":"4658","post_id":"1112","meta_key":"_badgeos_log_achievement_id","meta_value":null}},{"data":{"meta_id":"4659","post_id":"1113","meta_key":"_badgeos_log_achievement_id","meta_value":null}}]