[{"data":{"meta_id":"5240","post_id":"1390","meta_key":"_vc_post_settings","meta_value":"a:1:{s:10:\"vc_grid_id\";a:0:{}}"}},{"data":{"meta_id":"5241","post_id":"1390","meta_key":"_edit_last","meta_value":"2"}},{"data":{"meta_id":"5242","post_id":"1390","meta_key":"_wp_page_template","meta_value":"default"}},{"data":{"meta_id":"5243","post_id":"1391","meta_key":"_wpb_vc_js_status","meta_value":"false"}},{"data":{"meta_id":"5244","post_id":"1391","meta_key":"_vc_post_settings","meta_value":"a:1:{s:10:\"vc_grid_id\";a:0:{}}"}},{"data":{"meta_id":"5245","post_id":"1391","meta_key":"_badgeos_log_achievement_id","meta_value":null}},{"data":{"meta_id":"5246","post_id":"1390","meta_key":"_wpb_vc_js_status","meta_value":"false"}},{"data":{"meta_id":"5247","post_id":"1390","meta_key":"_edit_lock","meta_value":"1463259908:2"}},{"data":{"meta_id":"5248","post_id":"1393","meta_key":"_badgeos_log_achievement_id","meta_value":null}},{"data":{"meta_id":"5249","post_id":"1394","meta_key":"_badgeos_log_achievement_id","meta_value":null}},{"data":{"meta_id":"5251","post_id":"1396","meta_key":"_badgeos_log_achievement_id","meta_value":null}},{"data":{"meta_id":"5252","post_id":"1397","meta_key":"_badgeos_log_achievement_id","meta_value":null}},{"data":{"meta_id":"5253","post_id":"1040","meta_key":"quiz_pro_id_1","meta_value":"1"}},{"data":{"meta_id":"5254","post_id":"1040","meta_key":"quiz_pro_id","meta_value":"1"}},{"data":{"meta_id":"5255","post_id":"1043","meta_key":"quiz_pro_id_2","meta_value":"2"}},{"data":{"meta_id":"5256","post_id":"1043","meta_key":"quiz_pro_id","meta_value":"2"}},{"data":{"meta_id":"5257","post_id":"1046","meta_key":"quiz_pro_id_3","meta_value":"3"}},{"data":{"meta_id":"5258","post_id":"1046","meta_key":"quiz_pro_id","meta_value":"3"}},{"data":{"meta_id":"5259","post_id":"1049","meta_key":"quiz_pro_id_4","meta_value":"4"}},{"data":{"meta_id":"5260","post_id":"1049","meta_key":"quiz_pro_id","meta_value":"4"}}]